inferfuzzy/__init__.py
inferfuzzy/__main__.py
inferfuzzy/base_set.py
inferfuzzy/base_var.py
inferfuzzy/defuzzifications/__init__.py
inferfuzzy/defuzzifications/bisection_defuzzification.py
inferfuzzy/defuzzifications/centroid_defuzzification.py
inferfuzzy/defuzzifications/lom_defuzzification.py
inferfuzzy/defuzzifications/mom_defuzzification.py
inferfuzzy/defuzzifications/som_defuzzification.py
inferfuzzy/defuzzifications/utils.py
inferfuzzy/inference_system.py
inferfuzzy/main.py
inferfuzzy/membership.py
inferfuzzy/memberships/__init__.py
inferfuzzy/memberships/gamma_membership.py
inferfuzzy/memberships/gaussian_membership.py
inferfuzzy/memberships/l_membership.py
inferfuzzy/memberships/lambda_membership.py
inferfuzzy/memberships/pi_membership.py
inferfuzzy/memberships/s_membership.py
inferfuzzy/memberships/z_membership.py
inferfuzzy/predicates.py
inferfuzzy/rule.py
inferfuzzy/rules/__init__.py
inferfuzzy/rules/larsen_rule.py
inferfuzzy/rules/mamdani_rule.py
inferfuzzy/set.py
inferfuzzy/set_factory.py
inferfuzzy/systems/__init__.py
inferfuzzy/systems/larsen_system.py
inferfuzzy/systems/mamdani_system.py
inferfuzzy/var.py
inferfuzzy/var_factory.py
inferfuzzy-0.1.4.dist-info/entry_points.txt
inferfuzzy-0.1.4.dist-info/LICENSE
inferfuzzy-0.1.4.dist-info/WHEEL
inferfuzzy-0.1.4.dist-info/METADATA
inferfuzzy-0.1.4.dist-info/RECORD
