Metadata-Version: 2.1
Name: inferfuzzy
Version: 0.1.4
Summary: Fuzzy Inference System in Python
Home-page: https://github.com/leynier/inferfuzzy
License: MIT
Author: leynier
Author-email: leynier41@gmail.com
Requires-Python: >=3.8,<4.0
Classifier: License :: OSI Approved :: MIT License
Classifier: Programming Language :: Python :: 3
Classifier: Programming Language :: Python :: 3.8
Classifier: Programming Language :: Python :: 3.9
Requires-Dist: matplotlib (>=3.3.3,<4.0.0)
Requires-Dist: numpy (>=1.19.4,<2.0.0)
Requires-Dist: typer (>=0.3.2,<0.4.0)
Project-URL: Documentation, https://github.com/leynier/inferfuzzy
Project-URL: Repository, https://github.com/leynier/inferfuzzy
